thumbor_plugins/optimizers/mozjpeg/__init__.py
thumbor_plugins/optimizers/mozjpeg/config.py
thumbor_plugins_mozjpeg-0.1.4.dist-info/METADATA
thumbor_plugins_mozjpeg-0.1.4.dist-info/WHEEL
thumbor_plugins_mozjpeg-0.1.4.dist-info/top_level.txt
thumbor_plugins_mozjpeg-0.1.4.dist-info/RECORD
