Metadata-Version: 2.1
Name: thumbor-plugins-mozjpeg
Version: 0.1.4
Summary: Thumbor optimizer to run mozjpeg
Home-page: https://github.com/thumbor/thumbor-plugins
Author: Guilherme Souza
Author-email: guilherme@souza.tech
License: MIT
Keywords: thumbor optimizers mozjpeg
Classifier: Development Status :: 4 - Beta
Classifier: Intended Audience :: Developers
Classifier: License :: OSI Approved :: MIT License
Classifier: Natural Language :: English
Classifier: Operating System :: MacOS
Classifier: Operating System :: POSIX :: Linux
Classifier: Programming Language :: Python :: 3
Classifier: Programming Language :: Python :: 3.7
Classifier: Programming Language :: Python :: 3.8
Classifier: Programming Language :: Python :: 3 :: Only
Classifier: Topic :: Internet :: WWW/HTTP :: Dynamic Content
Classifier: Topic :: Multimedia :: Graphics :: Presentation
